LICENSE.txt
README.md
setup.py
v4/__init__.py
v4/vd.py
v4/vx.py
v4.egg-info/PKG-INFO
v4.egg-info/SOURCES.txt
v4.egg-info/dependency_links.txt
v4.egg-info/top_level.txt