Metadata-Version: 2.1
Name: v4
Version: 0.2.1
Summary: python tools for v4 images
Home-page: https://www.via.cornell.edu/visionx
Author: Anthony P. Reeves
Author-email: reeves@d4vision.com
License: GPL
Keywords: images
Classifier: Development Status :: 4 - Beta
License-File: LICENSE.txt
